{
  "resolvedId": "/Users/andreapuglisi/Desktop/andreapuglisi.io/node_modules/nuxt/dist/app/composables/chunk.js",
  "transforms": [
    {
      "name": "vite:load-fallback",
      "result": "import destr from \"destr\";\nimport { useNuxtApp } from \"../nuxt.js\";\nexport function reloadNuxtApp(options = {}) {\n  if (import.meta.server) {\n    return;\n  }\n  const path = options.path || window.location.pathname;\n  let handledPath = {};\n  try {\n    handledPath = destr(sessionStorage.getItem(\"nuxt:reload\") || \"{}\");\n  } catch {\n  }\n  if (options.force || handledPath?.path !== path || handledPath?.expires < Date.now()) {\n    try {\n      sessionStorage.setItem(\"nuxt:reload\", JSON.stringify({ path, expires: Date.now() + (options.ttl ?? 1e4) }));\n    } catch {\n    }\n    if (options.persistState) {\n      try {\n        sessionStorage.setItem(\"nuxt:reload:state\", JSON.stringify({ state: useNuxtApp().payload.state }));\n      } catch {\n      }\n    }\n    if (window.location.pathname !== path) {\n      window.location.href = path;\n    } else {\n      window.location.reload();\n    }\n  }\n}\n",
      "start": 1702568942742,
      "end": 1702568942836,
      "sourcemaps": null
    },
    {
      "name": "nuxt:layer-aliasing",
      "start": 1702568942836,
      "end": 1702568942836,
      "order": "pre"
    },
    {
      "name": "nuxt:server-devonly:transform",
      "start": 1702568942836,
      "end": 1702568942836,
      "order": "pre"
    },
    {
      "name": "nuxt:client-fallback-auto-id",
      "start": 1702568942836,
      "end": 1702568942836,
      "order": "pre"
    },
    {
      "name": "vite:css",
      "start": 1702568942836,
      "end": 1702568942836,
      "order": "normal"
    },
    {
      "name": "vite:esbuild",
      "start": 1702568942836,
      "end": 1702568942836,
      "order": "normal"
    },
    {
      "name": "vite:json",
      "start": 1702568942836,
      "end": 1702568942836,
      "order": "normal"
    },
    {
      "name": "vite:worker",
      "start": 1702568942836,
      "end": 1702568942836,
      "order": "normal"
    },
    {
      "name": "vite:vue",
      "start": 1702568942836,
      "end": 1702568942836,
      "order": "normal"
    },
    {
      "name": "vite:vue-jsx",
      "start": 1702568942836,
      "end": 1702568942836,
      "order": "normal"
    },
    {
      "name": "replace",
      "start": 1702568942836,
      "end": 1702568942837,
      "order": "normal"
    },
    {
      "name": "nuxt:remove-plugin-metadata",
      "start": 1702568942837,
      "end": 1702568942837,
      "order": "normal"
    },
    {
      "name": "nuxt:chunk-error",
      "start": 1702568942837,
      "end": 1702568942837,
      "order": "normal"
    },
    {
      "name": "nuxt:components:imports",
      "start": 1702568942837,
      "end": 1702568942837,
      "order": "normal"
    },
    {
      "name": "replace",
      "result": "import destr from \"destr\";\nimport { useNuxtApp } from \"../nuxt.js\";\nexport function reloadNuxtApp(options = {}) {\n  if (false) {\n    return;\n  }\n  const path = options.path || window.location.pathname;\n  let handledPath = {};\n  try {\n    handledPath = destr(sessionStorage.getItem(\"nuxt:reload\") || \"{}\");\n  } catch {\n  }\n  if (options.force || handledPath?.path !== path || handledPath?.expires < Date.now()) {\n    try {\n      sessionStorage.setItem(\"nuxt:reload\", JSON.stringify({ path, expires: Date.now() + (options.ttl ?? 1e4) }));\n    } catch {\n    }\n    if (options.persistState) {\n      try {\n        sessionStorage.setItem(\"nuxt:reload:state\", JSON.stringify({ state: useNuxtApp().payload.state }));\n      } catch {\n      }\n    }\n    if (window.location.pathname !== path) {\n      window.location.href = path;\n    } else {\n      window.location.reload();\n    }\n  }\n}\n",
      "start": 1702568942837,
      "end": 1702568942837,
      "order": "normal",
      "sourcemaps": {
        "version": 3,
        "sources": [
          ""
        ],
        "names": [],
        "mappings": "AAAA,CAAC,CAAC,CAAC,CAAC,CAAC,CAAC,CAAC,CAAC,CAAC,CAAC,CAAC,CAAC,CAAC,CAAC,CAAC,CAAC,CAAC,CAAC,CAAC,CAAC,CAAC,CAAC,CAAC,CAAC,CAAC,CAAC;AAC1B,CAAC,CAAC,CAAC,CAAC,CAAC,CAAC,CAAC,CAAC,CAAC,CAAC,CAAC,CAAC,CAAC,CAAC,CAAC,CAAC,CAAC,CAAC,CAAC,CAAC,CAAC,CAAC,CAAC,CAAC,CAAC,CAAC,CAAC,CAAC,CAAC,CAAC,CAAC,CAAC,CAAC,CAAC,CAAC,CAAC,CAAC,CAAC,CAAC,CAAC;AACxC,CAAC,CAAC,CAAC,CAAC,CAAC,CAAC,CAAC,CAAC,CAAC,CAAC,CAAC,CAAC,CAAC,CAAC,CAAC,CAAC,CAAC,CAAC,CAAC,CAAC,CAAC,CAAC,CAAC,CAAC,CAAC,CAAC,CAAC,CAAC,CAAC,CAAC,CAAC,CAAC,CAAC,CAAC,CAAC,CAAC,CAAC,CAAC,CAAC,CAAC,CAAC,CAAC,CAAC,CAAC,CAAC;AAC7C,CAAC,CAAC,CAAC,CAAC,CAAC,CAAC,KAAkB,CAAC,CAAC,CAAC;AAC3B,CAAC,CAAC,CAAC,CAAC,CAAC,CAAC,CAAC,CAAC,CAAC,CAAC,CAAC;AACX,CAAC,CAAC,CAAC;AACH,CAAC,CAAC,CAAC,CAAC,CAAC,CAAC,CAAC,CAAC,CAAC,CAAC,CAAC,CAAC,CAAC,CAAC,CAAC,CAAC,CAAC,CAAC,CAAC,CAAC,CAAC,CAAC,CAAC,CAAC,CAAC,CAAC,CAAC,CAAC,CAAC,CAAC,CAAC,CAAC,CAAC,CAAC,CAAC,CAAC,CAAC,CAAC,CAAC,CAAC,CAAC,CAAC,CAAC,CAAC,CAAC,CAAC,CAAC,CAAC,CAAC,CAAC,CAAC,CAAC,CAAC,CAAC,CAAC,CAAC;AACxD,CAAC,CAAC,CAAC,CAAC,CAAC,CAAC,CAAC,CAAC,CAAC,CAAC,CAAC,CAAC,CAAC,CAAC,CAAC,CAAC,CAAC,CAAC,CAAC,CAAC,CAAC,CAAC,CAAC;AACvB,CAAC,CAAC,CAAC,CAAC,CAAC,CAAC,CAAC;AACP,CAAC,CAAC,CAAC,CAAC,CAAC,CAAC,CAAC,CAAC,CAAC,CAAC,CAAC,CAAC,CAAC,CAAC,CAAC,CAAC,CAAC,CAAC,CAAC,CAAC,CAAC,CAAC,CAAC,CAAC,CAAC,CAAC,CAAC,CAAC,CAAC,CAAC,CAAC,CAAC,CAAC,CAAC,CAAC,CAAC,CAAC,CAAC,CAAC,CAAC,CAAC,CAAC,CAAC,CAAC,CAAC,CAAC,CAAC,CAAC,CAAC,CAAC,CAAC,CAAC,CAAC,CAAC,CAAC,CAAC,CAAC,CAAC,CAAC,CAAC,CAAC,CAAC,CAAC,CAAC,CAAC,CAAC,CAAC,CAAC,CAAC,CAAC,CAAC;AACvE,CAAC,CAAC,CAAC,CAAC,CAAC,CAAC,CAAC,CAAC,CAAC,CAAC,CAAC;AACX,CAAC,CAAC,CAAC;AACH,CAAC,CAAC,CAAC,CAAC,CAAC,CAAC,CAAC,CAAC,CAAC,CAAC,CAAC,CAAC,CAAC,CAAC,CAAC,CAAC,CAAC,CAAC,CAAC,CAAC,CAAC,CAAC,CAAC,CAAC,CAAC,CAAC,CAAC,CAAC,CAAC,CAAC,CAAC,CAAC,CAAC,CAAC,CAAC,CAAC,CAAC,CAAC,CAAC,CAAC,CAAC,CAAC,CAAC,CAAC,CAAC,CAAC,CAAC,CAAC,CAAC,CAAC,CAAC,CAAC,CAAC,CAAC,CAAC,CAAC,CAAC,CAAC,CAAC,CAAC,CAAC,CAAC,CAAC,CAAC,CAAC,CAAC,CAAC,CAAC,CAAC,CAAC,CAAC,CAAC,CAAC,CAAC,CAAC,CAAC,CAAC,CAAC,CAAC,CAAC,CAAC,CAAC,CAAC,CAAC,CAAC,CAAC,CAAC,CAAC,CAAC;AACzF,CAAC,CAAC,CAAC,CAAC,CAAC,CAAC,CAAC,CAAC,CAAC;AACT,CAAC,CAAC,CAAC,CAAC,CAAC,CAAC,CAAC,CAAC,CAAC,CAAC,CAAC,CAAC,CAAC,CAAC,CAAC,CAAC,CAAC,CAAC,CAAC,CAAC,CAAC,CAAC,CAAC,CAAC,CAAC,CAAC,CAAC,CAAC,CAAC,CAAC,CAAC,CAAC,CAAC,CAAC,CAAC,CAAC,CAAC,CAAC,CAAC,CAAC,CAAC,CAAC,CAAC,CAAC,CAAC,CAAC,CAAC,CAAC,CAAC,CAAC,CAAC,CAAC,CAAC,CAAC,CAAC,CAAC,CAAC,CAAC,CAAC,CAAC,CAAC,CAAC,CAAC,CAAC,CAAC,CAAC,CAAC,CAAC,CAAC,CAAC,CAAC,CAAC,CAAC,CAAC,CAAC,CAAC,CAAC,CAAC,CAAC,CAAC,CAAC,CAAC,CAAC,CAAC,CAAC,CAAC,CAAC,CAAC,CAAC,CAAC,CAAC,CAAC,CAAC,CAAC,CAAC,CAAC,CAAC,CAAC,CAAC,CAAC,CAAC,CAAC,CAAC,CAAC,CAAC,CAAC,CAAC,CAAC,CAAC,CAAC,CAAC,CAAC,CAAC,CAAC;AAClH,CAAC,CAAC,CAAC,CAAC,CAAC,CAAC,CAAC,CAAC,CAAC,CAAC,CAAC,CAAC,CAAC;AACb,CAAC,CAAC,CAAC,CAAC,CAAC;AACL,CAAC,CAAC,CAAC,CAAC,CAAC,CAAC,CAAC,CAAC,CAAC,CAAC,CAAC,CAAC,CAAC,CAAC,CAAC,CAAC,CAAC,CAAC,CAAC,CAAC,CAAC,CAAC,CAAC,CAAC,CAAC,CAAC,CAAC,CAAC,CAAC,CAAC,CAAC;AAC/B,CAAC,CAAC,CAAC,CAAC,CAAC,CAAC,CAAC,CAAC,CAAC,CAAC,CAAC;AACX,CAAC,CAAC,CAAC,CAAC,CAAC,CAAC,CAAC,CAAC,CAAC,CAAC,CAAC,CAAC,CAAC,CAAC,CAAC,CAAC,CAAC,CAAC,CAAC,CAAC,CAAC,CAAC,CAAC,CAAC,CAAC,CAAC,CAAC,CAAC,CAAC,CAAC,CAAC,CAAC,CAAC,CAAC,CAAC,CAAC,CAAC,CAAC,CAAC,CAAC,CAAC,CAAC,CAAC,CAAC,CAAC,CAAC,CAAC,CAAC,CAAC,CAAC,CAAC,CAAC,CAAC,CAAC,CAAC,CAAC,CAAC,CAAC,CAAC,CAAC,CAAC,CAAC,CAAC,CAAC,CAAC,CAAC,CAAC,CAAC,CAAC,CAAC,CAAC,CAAC,CAAC,CAAC,CAAC,CAAC,CAAC,CAAC,CAAC,CAAC,CAAC,CAAC,CAAC,CAAC,CAAC,CAAC,CAAC,CAAC,CAAC,CAAC,CAAC,CAAC,CAAC,CAAC,CAAC,CAAC,CAAC,CAAC,CAAC,CAAC,CAAC,CAAC,CAAC,CAAC,CAAC,CAAC,CAAC;AAC3G,CAAC,CAAC,CAAC,CAAC,CAAC,CAAC,CAAC,CAAC,CAAC,CAAC,CAAC,CAAC,CAAC,CAAC,CAAC;AACf,CAAC,CAAC,CAAC,CAAC,CAAC,CAAC,CAAC;AACP,CAAC,CAAC,CAAC,CAAC,CAAC;AACL,CAAC,CAAC,CAAC,CAAC,CAAC,CAAC,CAAC,CAAC,CAAC,CAAC,CAAC,CAAC,CAAC,CAAC,CAAC,CAAC,CAAC,CAAC,CAAC,CAAC,CAAC,CAAC,CAAC,CAAC,CAAC,CAAC,CAAC,CAAC,CAAC,CAAC,CAAC,CAAC,CAAC,CAAC,CAAC,CAAC,CAAC,CAAC,CAAC,CAAC,CAAC,CAAC,CAAC,CAAC;AAC5C,CAAC,CAAC,CAAC,CAAC,CAAC,CAAC,CAAC,CAAC,CAAC,CAAC,CAAC,CAAC,CAAC,CAAC,CAAC,CAAC,CAAC,CAAC,CAAC,CAAC,CAAC,CAAC,CAAC,CAAC,CAAC,CAAC,CAAC,CAAC,CAAC,CAAC,CAAC,CAAC,CAAC,CAAC;AAClC,CAAC,CAAC,CAAC,CAAC,CAAC,CAAC,CAAC,CAAC,CAAC,CAAC,CAAC,CAAC;AACZ,CAAC,CAAC,CAAC,CAAC,CAAC,CAAC,CAAC,CAAC,CAAC,CAAC,CAAC,CAAC,CAAC,CAAC,CAAC,CAAC,CAAC,CAAC,CAAC,CAAC,CAAC,CAAC,CAAC,CAAC,CAAC,CAAC,CAAC,CAAC,CAAC,CAAC,CAAC;AAC/B,CAAC,CAAC,CAAC,CAAC,CAAC;AACL,CAAC,CAAC,CAAC;AACH,CAAC;"
      }
    },
    {
      "name": "ssr-styles",
      "start": 1702568942837,
      "end": 1702568942837,
      "order": "normal"
    },
    {
      "name": "vite:define",
      "start": 1702568942837,
      "end": 1702568942837,
      "order": "normal"
    },
    {
      "name": "vite:css-post",
      "start": 1702568942837,
      "end": 1702568942837,
      "order": "normal"
    },
    {
      "name": "vite:build-html",
      "start": 1702568942837,
      "end": 1702568942837,
      "order": "normal"
    },
    {
      "name": "vite:worker-import-meta-url",
      "start": 1702568942837,
      "end": 1702568942837,
      "order": "normal"
    },
    {
      "name": "vite:asset-import-meta-url",
      "start": 1702568942837,
      "end": 1702568942837,
      "order": "normal"
    },
    {
      "name": "commonjs",
      "start": 1702568942837,
      "end": 1702568942838,
      "order": "normal"
    },
    {
      "name": "vite:dynamic-import-vars",
      "start": 1702568942838,
      "end": 1702568942838,
      "order": "normal"
    },
    {
      "name": "vite:import-glob",
      "start": 1702568942838,
      "end": 1702568942838,
      "order": "normal"
    },
    {
      "name": "nuxt:composable-keys",
      "start": 1702568942838,
      "end": 1702568942838,
      "order": "post"
    },
    {
      "name": "nuxt:imports-transform",
      "start": 1702568942838,
      "end": 1702568942838,
      "order": "post"
    },
    {
      "name": "unctx:transform",
      "start": 1702568942838,
      "end": 1702568942838,
      "order": "post"
    },
    {
      "name": "nuxt:pages-macros-transform",
      "start": 1702568942838,
      "end": 1702568942838,
      "order": "post"
    },
    {
      "name": "nuxt:runtime-paths-dep",
      "start": 1702568942838,
      "end": 1702568942838,
      "order": "post"
    },
    {
      "name": "nuxt:route-injection-plugin",
      "start": 1702568942838,
      "end": 1702568942838,
      "order": "post"
    },
    {
      "name": "nuxt:components-loader",
      "start": 1702568942838,
      "end": 1702568942838,
      "order": "post"
    },
    {
      "name": "nuxt:tree-shake-composables:transform",
      "start": 1702568942838,
      "end": 1702568942838,
      "order": "post"
    },
    {
      "name": "vite:build-import-analysis",
      "start": 1702568942838,
      "end": 1702568942838,
      "order": "normal"
    },
    {
      "name": "vite:reporter",
      "start": 1702568942838,
      "end": 1702568942838,
      "order": "normal"
    }
  ]
}
