{
  "resolvedId": "/Users/andreapuglisi/Desktop/andreapuglisi.io/node_modules/nuxt/dist/app/middleware/manifest-route-rule.js",
  "transforms": [
    {
      "name": "vite:load-fallback",
      "result": "import { defineNuxtRouteMiddleware } from \"../composables/router.js\";\nimport { getRouteRules } from \"../composables/manifest.js\";\nexport default defineNuxtRouteMiddleware(async (to) => {\n  if (import.meta.server || import.meta.test) {\n    return;\n  }\n  const rules = await getRouteRules(to.path);\n  if (rules.redirect) {\n    return rules.redirect;\n  }\n});\n",
      "start": 1702568942710,
      "end": 1702568942830,
      "sourcemaps": null
    },
    {
      "name": "nuxt:layer-aliasing",
      "start": 1702568942830,
      "end": 1702568942830,
      "order": "pre"
    },
    {
      "name": "nuxt:server-devonly:transform",
      "start": 1702568942830,
      "end": 1702568942830,
      "order": "pre"
    },
    {
      "name": "nuxt:client-fallback-auto-id",
      "start": 1702568942830,
      "end": 1702568942830,
      "order": "pre"
    },
    {
      "name": "vite:css",
      "start": 1702568942830,
      "end": 1702568942830,
      "order": "normal"
    },
    {
      "name": "vite:esbuild",
      "start": 1702568942830,
      "end": 1702568942830,
      "order": "normal"
    },
    {
      "name": "vite:json",
      "start": 1702568942830,
      "end": 1702568942830,
      "order": "normal"
    },
    {
      "name": "vite:worker",
      "start": 1702568942830,
      "end": 1702568942830,
      "order": "normal"
    },
    {
      "name": "vite:vue",
      "start": 1702568942830,
      "end": 1702568942830,
      "order": "normal"
    },
    {
      "name": "vite:vue-jsx",
      "start": 1702568942830,
      "end": 1702568942830,
      "order": "normal"
    },
    {
      "name": "replace",
      "start": 1702568942830,
      "end": 1702568942830,
      "order": "normal"
    },
    {
      "name": "nuxt:remove-plugin-metadata",
      "start": 1702568942830,
      "end": 1702568942830,
      "order": "normal"
    },
    {
      "name": "nuxt:chunk-error",
      "start": 1702568942830,
      "end": 1702568942830,
      "order": "normal"
    },
    {
      "name": "nuxt:components:imports",
      "start": 1702568942830,
      "end": 1702568942830,
      "order": "normal"
    },
    {
      "name": "replace",
      "result": "import { defineNuxtRouteMiddleware } from \"../composables/router.js\";\nimport { getRouteRules } from \"../composables/manifest.js\";\nexport default defineNuxtRouteMiddleware(async (to) => {\n  if (false || false) {\n    return;\n  }\n  const rules = await getRouteRules(to.path);\n  if (rules.redirect) {\n    return rules.redirect;\n  }\n});\n",
      "start": 1702568942830,
      "end": 1702568942830,
      "order": "normal",
      "sourcemaps": {
        "version": 3,
        "sources": [
          ""
        ],
        "names": [],
        "mappings": "AAAA,CAAC,CAAC,CAAC,CAAC,CAAC,CAAC,CAAC,CAAC,CAAC,CAAC,CAAC,CAAC,CAAC,CAAC,CAAC,CAAC,CAAC,CAAC,CAAC,CAAC,CAAC,CAAC,CAAC,CAAC,CAAC,CAAC,CAAC,CAAC,CAAC,CAAC,CAAC,CAAC,CAAC,CAAC,CAAC,CAAC,CAAC,CAAC,CAAC,CAAC,CAAC,CAAC,CAAC,CAAC,CAAC,CAAC,CAAC,CAAC,CAAC,CAAC,CAAC,CAAC,CAAC,CAAC,CAAC,CAAC,CAAC,CAAC,CAAC,CAAC,CAAC,CAAC,CAAC,CAAC,CAAC,CAAC,CAAC,CAAC,CAAC;AACrE,CAAC,CAAC,CAAC,CAAC,CAAC,CAAC,CAAC,CAAC,CAAC,CAAC,CAAC,CAAC,CAAC,CAAC,CAAC,CAAC,CAAC,CAAC,CAAC,CAAC,CAAC,CAAC,CAAC,CAAC,CAAC,CAAC,CAAC,CAAC,CAAC,CAAC,CAAC,CAAC,CAAC,CAAC,CAAC,CAAC,CAAC,CAAC,CAAC,CAAC,CAAC,CAAC,CAAC,CAAC,CAAC,CAAC,CAAC,CAAC,CAAC,CAAC,CAAC,CAAC,CAAC,CAAC,CAAC,CAAC,CAAC,CAAC,CAAC;AAC3D,CAAC,CAAC,CAAC,CAAC,CAAC,CAAC,CAAC,CAAC,CAAC,CAAC,CAAC,CAAC,CAAC,CAAC,CAAC,CAAC,CAAC,CAAC,CAAC,CAAC,CAAC,CAAC,CAAC,CAAC,CAAC,CAAC,CAAC,CAAC,CAAC,CAAC,CAAC,CAAC,CAAC,CAAC,CAAC,CAAC,CAAC,CAAC,CAAC,CAAC,CAAC,CAAC,CAAC,CAAC,CAAC,CAAC,CAAC,CAAC,CAAC,CAAC,CAAC,CAAC,CAAC,CAAC,CAAC,CAAC;AACxD,CAAC,CAAC,CAAC,CAAC,CAAC,CAAC,KAAkB,CAAC,CAAC,CAAC,CAAC,KAAgB,CAAC,CAAC,CAAC;AAC/C,CAAC,CAAC,CAAC,CAAC,CAAC,CAAC,CAAC,CAAC,CAAC,CAAC,CAAC;AACX,CAAC,CAAC,CAAC;AACH,CAAC,CAAC,CAAC,CAAC,CAAC,CAAC,CAAC,CAAC,CAAC,CAAC,CAAC,CAAC,CAAC,CAAC,CAAC,CAAC,CAAC,CAAC,CAAC,CAAC,CAAC,CAAC,CAAC,CAAC,CAAC,CAAC,CAAC,CAAC,CAAC,CAAC,CAAC,CAAC,CAAC,CAAC,CAAC,CAAC,CAAC,CAAC,CAAC,CAAC,CAAC,CAAC,CAAC,CAAC,CAAC;AAC7C,CAAC,CAAC,CAAC,CAAC,CAAC,CAAC,CAAC,CAAC,CAAC,CAAC,CAAC,CAAC,CAAC,CAAC,CAAC,CAAC,CAAC,CAAC,CAAC,CAAC,CAAC,CAAC,CAAC;AACvB,CAAC,CAAC,CAAC,CAAC,CAAC,CAAC,CAAC,CAAC,CAAC,CAAC,CAAC,CAAC,CAAC,CAAC,CAAC,CAAC,CAAC,CAAC,CAAC,CAAC,CAAC,CAAC,CAAC,CAAC,CAAC,CAAC;AAC1B,CAAC,CAAC,CAAC;AACH,CAAC,CAAC,CAAC;"
      }
    },
    {
      "name": "ssr-styles",
      "start": 1702568942830,
      "end": 1702568942831,
      "order": "normal"
    },
    {
      "name": "vite:define",
      "start": 1702568942831,
      "end": 1702568942831,
      "order": "normal"
    },
    {
      "name": "vite:css-post",
      "start": 1702568942831,
      "end": 1702568942831,
      "order": "normal"
    },
    {
      "name": "vite:build-html",
      "start": 1702568942831,
      "end": 1702568942831,
      "order": "normal"
    },
    {
      "name": "vite:worker-import-meta-url",
      "start": 1702568942831,
      "end": 1702568942831,
      "order": "normal"
    },
    {
      "name": "vite:asset-import-meta-url",
      "start": 1702568942831,
      "end": 1702568942831,
      "order": "normal"
    },
    {
      "name": "commonjs",
      "start": 1702568942831,
      "end": 1702568942831,
      "order": "normal"
    },
    {
      "name": "vite:dynamic-import-vars",
      "start": 1702568942831,
      "end": 1702568942831,
      "order": "normal"
    },
    {
      "name": "vite:import-glob",
      "start": 1702568942831,
      "end": 1702568942831,
      "order": "normal"
    },
    {
      "name": "nuxt:composable-keys",
      "start": 1702568942831,
      "end": 1702568942831,
      "order": "post"
    },
    {
      "name": "nuxt:imports-transform",
      "start": 1702568942831,
      "end": 1702568942831,
      "order": "post"
    },
    {
      "name": "unctx:transform",
      "result": "/* _processed_nuxt_unctx_transform */\nimport { executeAsync as __executeAsync } from \"/Users/andreapuglisi/Desktop/andreapuglisi.io/node_modules/unctx/dist/index.mjs\";import { defineNuxtRouteMiddleware } from \"../composables/router.js\";\nimport { getRouteRules } from \"../composables/manifest.js\";\nexport default defineNuxtRouteMiddleware(async (to) => {let __temp, __restore;\n  if (false || false) {\n    return;\n  }\n  const rules = (([__temp,__restore]=__executeAsync(()=>getRouteRules(to.path))),__temp=await __temp,__restore(),__temp);\n  if (rules.redirect) {\n    return rules.redirect;\n  }\n},1);\n",
      "start": 1702568942831,
      "end": 1702568942831,
      "order": "post",
      "sourcemaps": {
        "version": 3,
        "sources": [
          ""
        ],
        "names": [],
        "mappings": "iIAAA,CAAC,CAAC,CAAC,CAAC,CAAC,CAAC,CAAC,CAAC,CAAC,CAAC,CAAC,CAAC,CAAC,CAAC,CAAC,CAAC,CAAC,CAAC,CAAC,CAAC,CAAC,CAAC,CAAC,CAAC,CAAC,CAAC,CAAC,CAAC,CAAC,CAAC,CAAC,CAAC,CAAC,CAAC,CAAC,CAAC,CAAC,CAAC,CAAC,CAAC,CAAC,CAAC,CAAC,CAAC,CAAC,CAAC,CAAC,CAAC,CAAC,CAAC,CAAC,CAAC,CAAC,CAAC,CAAC,CAAC,CAAC,CAAC,CAAC,CAAC,CAAC,CAAC,CAAC,CAAC,CAAC,CAAC,CAAC,CAAC,CAAC;AACrE,CAAC,CAAC,CAAC,CAAC,CAAC,CAAC,CAAC,CAAC,CAAC,CAAC,CAAC,CAAC,CAAC,CAAC,CAAC,CAAC,CAAC,CAAC,CAAC,CAAC,CAAC,CAAC,CAAC,CAAC,CAAC,CAAC,CAAC,CAAC,CAAC,CAAC,CAAC,CAAC,CAAC,CAAC,CAAC,CAAC,CAAC,CAAC,CAAC,CAAC,CAAC,CAAC,CAAC,CAAC,CAAC,CAAC,CAAC,CAAC,CAAC,CAAC,CAAC,CAAC,CAAC,CAAC,CAAC,CAAC,CAAC,CAAC,CAAC;AAC3D,CAAC,CAAC,CAAC,CAAC,CAAC,CAAC,CAAC,CAAC,CAAC,CAAC,CAAC,CAAC,CAAC,CAAC,CAAC,CAAC,CAAC,CAAC,CAAC,CAAC,CAAC,CAAC,CAAC,CAAC,CAAC,CAAC,CAAC,CAAC,CAAC,CAAC,CAAC,CAAC,CAAC,CAAC,CAAC,CAAC,CAAC,CAAC,CAAC,CAAC,CAAC,CAAC,CAAC,CAAC,CAAC,CAAC,CAAC,CAAC,CAAC,CAAC,CAAC,CAAC,CAAC,CAAC,CAAC,uBAAC;AACxD,CAAC,CAAC,CAAC,CAAC,CAAC,CAAC,CAAC,CAAC,CAAC,CAAC,CAAC,CAAC,CAAC,CAAC,CAAC,CAAC,CAAC,CAAC,CAAC,CAAC,CAAC,CAAC,CAAC;AACvB,CAAC,CAAC,CAAC,CAAC,CAAC,CAAC,CAAC,CAAC,CAAC,CAAC,CAAC;AACX,CAAC,CAAC,CAAC;AACH,CAAC,CAAC,CAAC,CAAC,CAAC,CAAC,CAAC,CAAC,CAAC,CAAC,CAAC,CAAC,CAAC,CAAC,CAAC,yCAAO,CAAC,CAAC,CAAC,CAAC,CAAC,CAAC,CAAC,CAAC,CAAC,CAAC,CAAC,CAAC,CAAC,CAAC,CAAC,CAAC,CAAC,CAAC,CAAC,CAAC,CAAC,2CAAC,CAAC;AAC7C,CAAC,CAAC,CAAC,CAAC,CAAC,CAAC,CAAC,CAAC,CAAC,CAAC,CAAC,CAAC,CAAC,CAAC,CAAC,CAAC,CAAC,CAAC,CAAC,CAAC,CAAC,CAAC,CAAC;AACvB,CAAC,CAAC,CAAC,CAAC,CAAC,CAAC,CAAC,CAAC,CAAC,CAAC,CAAC,CAAC,CAAC,CAAC,CAAC,CAAC,CAAC,CAAC,CAAC,CAAC,CAAC,CAAC,CAAC,CAAC,CAAC,CAAC;AAC1B,CAAC,CAAC,CAAC;AACH,GAAC,CAAC,CAAC;"
      }
    },
    {
      "name": "nuxt:pages-macros-transform",
      "start": 1702568942831,
      "end": 1702568942831,
      "order": "post"
    },
    {
      "name": "nuxt:runtime-paths-dep",
      "start": 1702568942831,
      "end": 1702568942831,
      "order": "post"
    },
    {
      "name": "nuxt:route-injection-plugin",
      "start": 1702568942831,
      "end": 1702568942831,
      "order": "post"
    },
    {
      "name": "nuxt:components-loader",
      "start": 1702568942831,
      "end": 1702568942831,
      "order": "post"
    },
    {
      "name": "nuxt:tree-shake-composables:transform",
      "start": 1702568942831,
      "end": 1702568942831,
      "order": "post"
    },
    {
      "name": "vite:build-import-analysis",
      "start": 1702568942831,
      "end": 1702568942831,
      "order": "normal"
    },
    {
      "name": "vite:reporter",
      "start": 1702568942831,
      "end": 1702568942831,
      "order": "normal"
    }
  ]
}
